.DS_Store
django_js_urls-0.1.1.dist-info/LICENSE.txt
django_js_urls-0.1.1.dist-info/METADATA
django_js_urls-0.1.1.dist-info/RECORD
django_js_urls-0.1.1.dist-info/WHEEL
django_js_urls-0.1.1.dist-info/top_level.txt
js_urls/__init__.py
js_urls/apps.py
js_urls/serializer.py
js_urls/views.py
js_urls/conf/__init__.py
js_urls/conf/settings.py
js_urls/templates/js_urls/js_urls.js
js_urls/utils/__init__.py
js_urls/utils/compat.py
js_urls/utils/text.py
