Metadata-Version: 2.1
Name: django-js-urls
Version: 0.1.1
Summary: A convenient helper to use Django URLs in Javascript.
Home-page: https://github.com/impak-finance/django-js-urls
Author: impak Finance
Author-email: tech@impakfinance.com
License: MIT
Keywords: django javascript js url urls helper
Platform: UNKNOWN
Classifier: Development Status :: 4 - Beta
Classifier: Environment :: Web Environment
Classifier: Framework :: Django
Classifier: Intended Audience :: Developers
Classifier: License :: OSI Approved :: MIT License
Classifier: Natural Language :: English
Classifier: Programming Language :: Python
Classifier: Programming Language :: Python :: 3
Classifier: Programming Language :: Python :: 3.4
Classifier: Programming Language :: Python :: 3.5
Classifier: Programming Language :: Python :: 3.6
Classifier: Programming Language :: Python :: 3.7
Requires-Dist: django (>=1.11)
